sensitive_variables/__init__.py
sensitive_variables-0.1.4.dist-info/LICENSE
sensitive_variables-0.1.4.dist-info/METADATA
sensitive_variables-0.1.4.dist-info/WHEEL
sensitive_variables-0.1.4.dist-info/top_level.txt
sensitive_variables-0.1.4.dist-info/RECORD
